odoo/addons/account_statement_import_camt/README.rst
odoo/addons/account_statement_import_camt/__init__.py
odoo/addons/account_statement_import_camt/__manifest__.py
odoo/addons/account_statement_import_camt/i18n/account_statement_import_camt.pot
odoo/addons/account_statement_import_camt/i18n/de.po
odoo/addons/account_statement_import_camt/i18n/es.po
odoo/addons/account_statement_import_camt/i18n/fa.po
odoo/addons/account_statement_import_camt/i18n/fi.po
odoo/addons/account_statement_import_camt/i18n/fr.po
odoo/addons/account_statement_import_camt/i18n/fr_CH.po
odoo/addons/account_statement_import_camt/i18n/gl.po
odoo/addons/account_statement_import_camt/i18n/hr.po
odoo/addons/account_statement_import_camt/i18n/it.po
odoo/addons/account_statement_import_camt/i18n/lt_LT.po
odoo/addons/account_statement_import_camt/i18n/nb_NO.po
odoo/addons/account_statement_import_camt/i18n/nl.po
odoo/addons/account_statement_import_camt/i18n/pt_BR.po
odoo/addons/account_statement_import_camt/i18n/pt_PT.po
odoo/addons/account_statement_import_camt/i18n/sl.po
odoo/addons/account_statement_import_camt/models/__init__.py
odoo/addons/account_statement_import_camt/models/account_journal.py
odoo/addons/account_statement_import_camt/models/account_statement_import.py
odoo/addons/account_statement_import_camt/models/account_statement_import_camt_parser.py
odoo/addons/account_statement_import_camt/readme/CONTRIBUTORS.md
odoo/addons/account_statement_import_camt/readme/CREDITS.md
odoo/addons/account_statement_import_camt/readme/DESCRIPTION.md
odoo/addons/account_statement_import_camt/readme/newsfragment/1_verbose_narration.feature
odoo/addons/account_statement_import_camt/static/description/icon.png
odoo/addons/account_statement_import_camt/static/description/index.html
odoo/addons/account_statement_import_camt/tests/__init__.py
odoo/addons/account_statement_import_camt/tests/test_import_bank_statement.py
odoo/addons/account_statement_import_camt/tests/samples/golden-camt053-no-ntry.pydata
odoo_addon_account_statement_import_camt-18.0.1.0.0.3.dist-info/METADATA
odoo_addon_account_statement_import_camt-18.0.1.0.0.3.dist-info/WHEEL
odoo_addon_account_statement_import_camt-18.0.1.0.0.3.dist-info/top_level.txt
odoo_addon_account_statement_import_camt-18.0.1.0.0.3.dist-info/RECORD
